{
 "cells": [
  {
   "cell_type": "markdown",
   "metadata": {},
   "source": [
    "An instructor is 1 op-code byte, followed by 0 or more operands.  \n",
    "The instruction encode type information about it's operands (eg: iadd to add int, ifloat to add floats, they have 2 different opcodes).  \n",
    "\n",
    "Several instructions has a prefix depending on the type of the operands\n",
    "- b: byte\n",
    "- s: short\n",
    "- i: int\n",
    "- l: long\n",
    "- f: float\n",
    "- d: double\n",
    "- c: char\n",
    "- a: reference\n",
    "\n",
    "Other where type are obvious doesn't have one.  \n",
    "There isn't an instruction for every type. Especially for byte, short, it's usually needed to use some extra conversion instructions."
   ]
  },
  {
   "cell_type": "markdown",
   "metadata": {},
   "source": [
    "# Load / Store\n",
    "\n",
    "- Tload: load local variable into operand stack\n",
    "- Tstore: store value into local variable from operand stack\n",
    "- Taload: load array value at index i into operand stack\n",
    "- Tastore: store value into array at index i from operand stack"
   ]
  },
  {
   "cell_type": "markdown",
   "metadata": {},
   "source": [
    "# Arithmetic\n",
    "\n",
    "- Tadd\n",
    "- Tsub\n",
    "- Tmul\n",
    "- Tdiv\n",
    "- Trem (modulo)\n",
    "- Tneg\n",
    "- Tshl (logical shift left)\n",
    "- Tshr (logical shift right)\n",
    "- Turshr (unsigned shift right)\n",
    "- Tor (bitwise or)\n",
    "- Tand (bitwise and)\n",
    "- Txor (bitwise xor)"
   ]
  },
  {
   "cell_type": "markdown",
   "metadata": {},
   "source": [
    "# Type conversion\n",
    "\n",
    "Used for explicit conversion in user code, or because of the lack of instructions for some types.  \n",
    "\n",
    "Widening:\n",
    "- i2T: int to long, float or double\n",
    "- l2T: long to float, double\n",
    "- f2d: float to double\n",
    "\n",
    "Narrowing:\n",
    "- i2T: int to byte, short, char\n",
    "- l2i: long to int\n",
    "- f2T: float to int, long\n",
    "- d2T: double to float, int, long"
   ]
  },
  {
   "cell_type": "markdown",
   "metadata": {},
   "source": [
    "# Object creation and manipulation\n",
    "\n",
    "- new: create new instance of class\n",
    "- newarray: create new array\n",
    "- getfield: get instance field value\n",
    "- putfield: set instance field value\n",
    "- getstatic: get static field value\n",
    "- putstatic: put static field value\n",
    "- arraylength: get size of array"
   ]
  },
  {
   "cell_type": "code",
   "execution_count": null,
   "metadata": {},
   "outputs": [],
   "source": [
    "# %load ./examples/Vec2fNew.java\n",
    "public class Vec2fNew\n",
    "{\n",
    "    private float _x;\n",
    "    private float _y;\n",
    "\n",
    "    public Vec2fNew(float x, float y)\n",
    "    {\n",
    "\t_x = x;\n",
    "\t_y = y;\n",
    "    }\n",
    "\n",
    "    public static Vec2fNew new_vec(float x, float y)\n",
    "    {\n",
    "\treturn new Vec2fNew(x, y);\n",
    "    }\n",
    "\n",
    "}\n"
   ]
  },
  {
   "cell_type": "code",
   "execution_count": null,
   "metadata": {},
   "outputs": [],
   "source": [
    "# %load ./examples/Vec2fNew.code.txt\n",
    "Compiled from \"Vec2fNew.java\"\n",
    "public class Vec2fNew {\n",
    "  public Vec2fNew(float, float);\n",
    "    Code:\n",
    "       0: aload_0\n",
    "       1: invokespecial #1                  // Method java/lang/Object.\"<init>\":()V\n",
    "       4: aload_0\n",
    "       5: fload_1\n",
    "       6: putfield      #7                  // Field _x:F\n",
    "       9: aload_0\n",
    "      10: fload_2\n",
    "      11: putfield      #13                 // Field _y:F\n",
    "      14: return\n",
    "\n",
    "  public static Vec2fNew new_vec(float, float);\n",
    "    Code:\n",
    "       0: new           #8                  // class Vec2fNew\n",
    "       3: dup\n",
    "       4: fload_0\n",
    "       5: fload_1\n",
    "       6: invokespecial #16                 // Method \"<init>\":(FF)V\n",
    "       9: areturn\n",
    "}\n"
   ]
  },
  {
   "cell_type": "code",
   "execution_count": null,
   "metadata": {},
   "outputs": [],
   "source": [
    "# %load ./examples/Vec2fGetSet.java\n",
    "public class Vec2fGetSet\n",
    "{\n",
    "    private float _x;\n",
    "    private float _y;\n",
    "\n",
    "    public float getX() { return _x; }\n",
    "    public float getY() { return _y; }\n",
    "    public void setX(float x) { _x = x; }\n",
    "    public void setY(float y) { _y = y; }\n",
    "}\n"
   ]
  },
  {
   "cell_type": "code",
   "execution_count": null,
   "metadata": {},
   "outputs": [],
   "source": [
    "# %load ./examples/Vec2fGetSet.code.txt\n",
    "Compiled from \"Vec2fGetSet.java\"\n",
    "public class Vec2fGetSet {\n",
    "  public Vec2fGetSet();\n",
    "    Code:\n",
    "       0: aload_0\n",
    "       1: invokespecial #1                  // Method java/lang/Object.\"<init>\":()V\n",
    "       4: return\n",
    "\n",
    "  public float getX();\n",
    "    Code:\n",
    "       0: aload_0\n",
    "       1: getfield      #7                  // Field _x:F\n",
    "       4: freturn\n",
    "\n",
    "  public float getY();\n",
    "    Code:\n",
    "       0: aload_0\n",
    "       1: getfield      #13                 // Field _y:F\n",
    "       4: freturn\n",
    "\n",
    "  public void setX(float);\n",
    "    Code:\n",
    "       0: aload_0\n",
    "       1: fload_1\n",
    "       2: putfield      #7                  // Field _x:F\n",
    "       5: return\n",
    "\n",
    "  public void setY(float);\n",
    "    Code:\n",
    "       0: aload_0\n",
    "       1: fload_1\n",
    "       2: putfield      #13                 // Field _y:F\n",
    "       5: return\n",
    "}\n"
   ]
  },
  {
   "cell_type": "code",
   "execution_count": null,
   "metadata": {},
   "outputs": [],
   "source": [
    "# %load ./examples/Counter.java\n",
    "public class Counter\n",
    "{\n",
    "\n",
    "    private static int _instances;\n",
    "\n",
    "    Counter()\n",
    "    {\n",
    "\t++_instances;\n",
    "    }\n",
    "\n",
    "    public static int get_instances() { return _instances; }\n",
    "\n",
    "}\n"
   ]
  },
  {
   "cell_type": "code",
   "execution_count": null,
   "metadata": {},
   "outputs": [],
   "source": [
    "# %load ./examples/Counter.code.txt\n",
    "Compiled from \"Counter.java\"\n",
    "public class Counter {\n",
    "  Counter();\n",
    "    Code:\n",
    "       0: aload_0\n",
    "       1: invokespecial #1                  // Method java/lang/Object.\"<init>\":()V\n",
    "       4: getstatic     #7                  // Field _instances:I\n",
    "       7: iconst_1\n",
    "       8: iadd\n",
    "       9: putstatic     #7                  // Field _instances:I\n",
    "      12: return\n",
    "\n",
    "  public static int get_instances();\n",
    "    Code:\n",
    "       0: getstatic     #7                  // Field _instances:I\n",
    "       3: ireturn\n",
    "}\n"
   ]
  },
  {
   "cell_type": "code",
   "execution_count": null,
   "metadata": {},
   "outputs": [],
   "source": [
    "# %load ./examples/MyVec.java\n",
    "public final class MyVec\n",
    "{\n",
    "\n",
    "    private int _data[];\n",
    "    private int _size;\n",
    "\n",
    "    MyVec()\n",
    "    {\n",
    "\t_data = new int[8];\n",
    "\t_size = 0;\n",
    "    }\n",
    "\n",
    "    public int getSize()\n",
    "    {\n",
    "\treturn _size;\n",
    "    }\n",
    "\n",
    "    public int getCapacity()\n",
    "    {\n",
    "\treturn _data.length;\n",
    "    }\n",
    "\n",
    "    public int getVal(int id)\n",
    "    {\n",
    "\treturn _data[id];\n",
    "    }\n",
    "\n",
    "    public void setVal(int id, int val)\n",
    "    {\n",
    "\t_data[id] = val;\n",
    "    }\n",
    "\n",
    "    public void push(int val)\n",
    "    {\n",
    "\treserve(_size + 1);\n",
    "\t_data[_size] = val;\n",
    "\t++_size;\n",
    "    }\n",
    "\n",
    "    public void reserve(int new_cap)\n",
    "    {\n",
    "\tint next_cap = getCapacity();\n",
    "\twhile (new_cap > next_cap)\n",
    "\t    next_cap *= 2;\n",
    "\tif (next_cap == getCapacity())\n",
    "\t    return;\n",
    "\t\n",
    "\tint[] new_data = new int[next_cap];\n",
    "\tfor (int i = 0; i < getSize(); ++i)\n",
    "\t    new_data[i] = _data[i];\n",
    "\t_data = new_data;\n",
    "    }\n",
    "\n",
    "}\n"
   ]
  },
  {
   "cell_type": "code",
   "execution_count": null,
   "metadata": {},
   "outputs": [],
   "source": [
    "# %load ./examples/MyVec.code.txt\n",
    "Compiled from \"MyVec.java\"\n",
    "public final class MyVec {\n",
    "  MyVec();\n",
    "    Code:\n",
    "       0: aload_0\n",
    "       1: invokespecial #1                  // Method java/lang/Object.\"<init>\":()V\n",
    "       4: aload_0\n",
    "       5: bipush        8\n",
    "       7: newarray       int\n",
    "       9: putfield      #7                  // Field _data:[I\n",
    "      12: aload_0\n",
    "      13: iconst_0\n",
    "      14: putfield      #13                 // Field _size:I\n",
    "      17: return\n",
    "\n",
    "  public int getSize();\n",
    "    Code:\n",
    "       0: aload_0\n",
    "       1: getfield      #13                 // Field _size:I\n",
    "       4: ireturn\n",
    "\n",
    "  public int getCapacity();\n",
    "    Code:\n",
    "       0: aload_0\n",
    "       1: getfield      #7                  // Field _data:[I\n",
    "       4: arraylength\n",
    "       5: ireturn\n",
    "\n",
    "  public int getVal(int);\n",
    "    Code:\n",
    "       0: aload_0\n",
    "       1: getfield      #7                  // Field _data:[I\n",
    "       4: iload_1\n",
    "       5: iaload\n",
    "       6: ireturn\n",
    "\n",
    "  public void setVal(int, int);\n",
    "    Code:\n",
    "       0: aload_0\n",
    "       1: getfield      #7                  // Field _data:[I\n",
    "       4: iload_1\n",
    "       5: iload_2\n",
    "       6: iastore\n",
    "       7: return\n",
    "\n",
    "  public void push(int);\n",
    "    Code:\n",
    "       0: aload_0\n",
    "       1: aload_0\n",
    "       2: getfield      #13                 // Field _size:I\n",
    "       5: iconst_1\n",
    "       6: iadd\n",
    "       7: invokevirtual #17                 // Method reserve:(I)V\n",
    "      10: aload_0\n",
    "      11: getfield      #7                  // Field _data:[I\n",
    "      14: aload_0\n",
    "      15: getfield      #13                 // Field _size:I\n",
    "      18: iload_1\n",
    "      19: iastore\n",
    "      20: aload_0\n",
    "      21: dup\n",
    "      22: getfield      #13                 // Field _size:I\n",
    "      25: iconst_1\n",
    "      26: iadd\n",
    "      27: putfield      #13                 // Field _size:I\n",
    "      30: return\n",
    "\n",
    "  public void reserve(int);\n",
    "    Code:\n",
    "       0: aload_0\n",
    "       1: invokevirtual #21                 // Method getCapacity:()I\n",
    "       4: istore_2\n",
    "       5: iload_1\n",
    "       6: iload_2\n",
    "       7: if_icmple     17\n",
    "      10: iload_2\n",
    "      11: iconst_2\n",
    "      12: imul\n",
    "      13: istore_2\n",
    "      14: goto          5\n",
    "      17: iload_2\n",
    "      18: aload_0\n",
    "      19: invokevirtual #21                 // Method getCapacity:()I\n",
    "      22: if_icmpne     26\n",
    "      25: return\n",
    "      26: iload_2\n",
    "      27: newarray       int\n",
    "      29: astore_3\n",
    "      30: iconst_0\n",
    "      31: istore        4\n",
    "      33: iload         4\n",
    "      35: aload_0\n",
    "      36: invokevirtual #25                 // Method getSize:()I\n",
    "      39: if_icmpge     59\n",
    "      42: aload_3\n",
    "      43: iload         4\n",
    "      45: aload_0\n",
    "      46: getfield      #7                  // Field _data:[I\n",
    "      49: iload         4\n",
    "      51: iaload\n",
    "      52: iastore\n",
    "      53: iinc          4, 1\n",
    "      56: goto          33\n",
    "      59: aload_0\n",
    "      60: aload_3\n",
    "      61: putfield      #7                  // Field _data:[I\n",
    "      64: return\n",
    "}\n"
   ]
  },
  {
   "cell_type": "markdown",
   "metadata": {},
   "source": [
    "# Operand stack management\n",
    "\n",
    "- pop: pop and ignore top value\n",
    "- pop2: pop and ignore top 2 values\n",
    "- dup: duplicate top value\n",
    "- dup2: duplicate top 2 values\n",
    "- swap: stap top 2 stack values"
   ]
  },
  {
   "cell_type": "markdown",
   "metadata": {},
   "source": [
    "# Conditional branching\n",
    "\n",
    "ifcond or if_cond (eg ifeq, ifne, if_icmple)\n",
    "\n",
    "Used for if/else and while code"
   ]
  },
  {
   "cell_type": "markdown",
   "metadata": {},
   "source": [
    "# Unconditional branching\n",
    "\n",
    "- goto: jump to some code in the function using a branch offset\n",
    "- goto_w: same as offset, but allowing bigger offset.\n",
    "- jsr: jump subroutine: jump to some code using a branch offset, and push return adress in stack\n",
    "- ret: return from a subroutine"
   ]
  },
  {
   "cell_type": "code",
   "execution_count": null,
   "metadata": {},
   "outputs": [],
   "source": [
    "# %load ./examples/Branching.java\n",
    "public class Branching\n",
    "{\n",
    "\n",
    "    public static void test_if(int p)\n",
    "    {\n",
    "\tint x;\n",
    "\tif (p > 3)\n",
    "\t    x = 5;\n",
    "    }\n",
    "\n",
    "    public static void test_if_else(int p)\n",
    "    {\n",
    "\tint x;\n",
    "\tif (p == 3)\n",
    "\t    x = 5;\n",
    "\telse\n",
    "\t    x = 7;\n",
    "    }\n",
    "\n",
    "    public static void test_while(int[] data)\n",
    "    {\n",
    "\tif (data == null)\n",
    "\t    return;\n",
    "\tint i = 0;\n",
    "\twhile (i < 4)\n",
    "\t{\n",
    "\t    i += 5;\n",
    "\t    data[0] = 6;\n",
    "\t}\n",
    "    }\n",
    "\n",
    "}\n"
   ]
  },
  {
   "cell_type": "code",
   "execution_count": null,
   "metadata": {},
   "outputs": [],
   "source": [
    "# %load ./examples/Branching.code.txt\n",
    "Compiled from \"Branching.java\"\n",
    "public class Branching {\n",
    "  public Branching();\n",
    "    Code:\n",
    "       0: aload_0\n",
    "       1: invokespecial #1                  // Method java/lang/Object.\"<init>\":()V\n",
    "       4: return\n",
    "\n",
    "  public static void test_if(int);\n",
    "    Code:\n",
    "       0: iload_0\n",
    "       1: iconst_3\n",
    "       2: if_icmple     7\n",
    "       5: iconst_5\n",
    "       6: istore_1\n",
    "       7: return\n",
    "\n",
    "  public static void test_if_else(int);\n",
    "    Code:\n",
    "       0: iload_0\n",
    "       1: iconst_3\n",
    "       2: if_icmpne     10\n",
    "       5: iconst_5\n",
    "       6: istore_1\n",
    "       7: goto          13\n",
    "      10: bipush        7\n",
    "      12: istore_1\n",
    "      13: return\n",
    "\n",
    "  public static void test_while(int[]);\n",
    "    Code:\n",
    "       0: aload_0\n",
    "       1: ifnonnull     5\n",
    "       4: return\n",
    "       5: iconst_0\n",
    "       6: istore_1\n",
    "       7: iload_1\n",
    "       8: iconst_4\n",
    "       9: if_icmpge     23\n",
    "      12: iinc          1, 5\n",
    "      15: aload_0\n",
    "      16: iconst_0\n",
    "      17: bipush        6\n",
    "      19: iastore\n",
    "      20: goto          7\n",
    "      23: return\n",
    "}\n"
   ]
  },
  {
   "cell_type": "markdown",
   "metadata": {},
   "source": [
    "# Method invocation\n",
    "\n",
    "- invokevirtual: call an instance method, performing dynamic dispatch\n",
    "- invokeinterface: call an interface method\n",
    "- invokespecial: special method, such as initialization method.\n",
    "- invokestatic: call a static method\n",
    "\n",
    "When calling a method, we pass arguments on the stack.  \n",
    "We return from a method using instruction Treturn, or just return for void functions.  \n",
    "The value we want to return is stored on top of the stack.  \n",
    "When returning from a method, the return value is on top of the stack."
   ]
  },
  {
   "cell_type": "code",
   "execution_count": null,
   "metadata": {},
   "outputs": [],
   "source": [
    "# %load ./examples/Fact.java\n",
    "public class Fact\n",
    "{\n",
    "\n",
    "    public static int get(int x)\n",
    "    {\n",
    "\tif (x <= 1)\n",
    "\t    return 1;\n",
    "\telse\n",
    "\t    return x * Fact.get(x - 1);\n",
    "    }\n",
    "\n",
    "}\n"
   ]
  },
  {
   "cell_type": "code",
   "execution_count": null,
   "metadata": {},
   "outputs": [],
   "source": [
    "# %load ./examples/Fact.code.txt\n",
    "Compiled from \"Fact.java\"\n",
    "public class Fact {\n",
    "  public Fact();\n",
    "    Code:\n",
    "       0: aload_0\n",
    "       1: invokespecial #1                  // Method java/lang/Object.\"<init>\":()V\n",
    "       4: return\n",
    "\n",
    "  public static int get(int);\n",
    "    Code:\n",
    "       0: iload_0\n",
    "       1: iconst_1\n",
    "       2: if_icmpgt     7\n",
    "       5: iconst_1\n",
    "       6: ireturn\n",
    "       7: iload_0\n",
    "       8: iload_0\n",
    "       9: iconst_1\n",
    "      10: isub\n",
    "      11: invokestatic  #7                  // Method get:(I)I\n",
    "      14: imul\n",
    "      15: ireturn\n",
    "}\n"
   ]
  },
  {
   "cell_type": "markdown",
   "metadata": {},
   "source": [
    "Refs:\n",
    "\n",
    "- [JVM specs (JSE 13)](https://docs.oracle.com/javase/specs/jvms/se13/jvms13.pdf)"
   ]
  }
 ],
 "metadata": {
  "kernelspec": {
   "display_name": "Python 3",
   "language": "python",
   "name": "python3"
  },
  "language_info": {
   "codemirror_mode": {
    "name": "ipython",
    "version": 3
   },
   "file_extension": ".py",
   "mimetype": "text/x-python",
   "name": "python",
   "nbconvert_exporter": "python",
   "pygments_lexer": "ipython3",
   "version": "3.6.9"
  }
 },
 "nbformat": 4,
 "nbformat_minor": 2
}
